mcsmt/__init__.py
mcsmt/__main__.py
mcsmt/info.py
mcsmt/logger.py
mcsmt/starter.py
mcsmt/utils.py
mcsmt/webApi.py
mcsmt/webApiRunner.py
mcsmt/client/__init__.py
mcsmt/client/main.py
mcsmt/mixed/__init__.py
mcsmt/mixed/about_ModLoader.txt
mcsmt/mixed/down.py
mcsmt/mixed/extdown.py
mcsmt/mixed/ezdns.py
mcsmt/mixed/moddown.py
mcsmt/server/__init__.py
mcsmt/server/gen.py
mcsmt/server/genconf.py
mcsmt/server/wdgen.py
mcsmt-0.3.0.2.dist-info/METADATA
mcsmt-0.3.0.2.dist-info/WHEEL
mcsmt-0.3.0.2.dist-info/licenses/LICENCE
mcsmt-0.3.0.2.dist-info/RECORD
