Metadata-Version: 2.1
Name: mcsmt
Version: 0.3.0.2
Summary: Simple file synchronization service (clients in the same package)
Project-URL: Homepage, https://github.com/ECSDevs/MCSMT
Project-URL: Bug Tracker, https://github.com/ECSDevs/MCSMT/issues
Project-URL: Support Me, https://afdian.net/a/mcsmt_transfer_tool
Author-email: ECSDevs <psbash@groupmail.com>
Maintainer-email: originalFactor <2438926613@qq.com>
License:                     GNU GENERAL PUBLIC LICENSE
License-File: LICENCE
Classifier: Development Status :: 4 - Beta
Classifier: License :: OSI Approved :: GNU General Public License v3 (GPLv3)
Classifier: Operating System :: OS Independent
Classifier: Programming Language :: Python :: 3
Requires-Python: >=3.0
Requires-Dist: dnspython
Requires-Dist: fastapi
Requires-Dist: httpx
Requires-Dist: watchdog
